dtseqlib/__init__.py
dtseqlib/sequence.py
dtseqlib-1.0.dist-info/LICENSE
dtseqlib-1.0.dist-info/METADATA
dtseqlib-1.0.dist-info/WHEEL
dtseqlib-1.0.dist-info/top_level.txt
dtseqlib-1.0.dist-info/RECORD
