Metadata-Version: 2.1
Name: dtseqlib
Version: 1.0
Summary: Sequence data type.
Home-page: https://github.com/BesBobowyy/dtseqlib
Author: BesBobowyy
Author-email: 
Requires-Python: >3.0
License-File: LICENSE
